dada_openapi_client/__init__.py
dada_openapi_client/dada_client.py
dada_openapi_client-1.0.3.dist-info/LICENSE
dada_openapi_client-1.0.3.dist-info/METADATA
dada_openapi_client-1.0.3.dist-info/WHEEL
dada_openapi_client-1.0.3.dist-info/top_level.txt
dada_openapi_client-1.0.3.dist-info/RECORD
