Metadata-Version: 2.1
Name: dada-openapi-client
Version: 1.0.3
Summary: 达达签名数据封装
Home-page: https://github.com/longweiqiang/dada_openapi_python
Author: Weiqiang.long
License: UNKNOWN
Platform: UNKNOWN
Classifier: Programming Language :: Python :: 3
Classifier: License :: OSI Approved :: MIT License
Classifier: Operating System :: OS Independent
